octo_pipeline_python/backends/tar/__init__.py
octo_pipeline_python/backends/tar/tar_backend.py
octo_pipeline_python/backends/tar/actions/__init__.py
octo_pipeline_python/backends/tar/actions/tar_extract.py
octo_pipeline_python/backends/tar/models/__init__.py
octo_pipeline_python/backends/tar/models/tar_model.py
octo_pipeline_backend_tar_python-1.3.2.dist-info/LICENSE.txt
octo_pipeline_backend_tar_python-1.3.2.dist-info/METADATA
octo_pipeline_backend_tar_python-1.3.2.dist-info/README.md
octo_pipeline_backend_tar_python-1.3.2.dist-info/WHEEL
octo_pipeline_backend_tar_python-1.3.2.dist-info/top_level.txt
octo_pipeline_backend_tar_python-1.3.2.dist-info/RECORD
